{
  "actions": [
    {
      "acted_at": "2014-09-15", 
      "committees": [
        "SSHR"
      ], 
      "references": [], 
      "status": "REFERRED", 
      "text": "Read twice and referred to the Committee on Health, Education, Labor, and Pensions.", 
      "type": "referral"
    }
  ], 
  "amendments": [], 
  "bill_id": "s2804-113", 
  "bill_type": "s", 
  "by_request": false, 
  "committees": [
    {
      "activity": [
        "referral"
      ], 
      "committee": "Senate Health, Education, Labor, and Pensions", 
      "committee_id": "SSHR"
    }
  ], 
  "congress": "113", 
  "cosponsors": [
    {
      "district": null, 
      "name": "Booker, Cory A.", 
      "sponsored_at": "2014-09-15", 
      "state": "NJ", 
      "thomas_id": "02194", 
      "title": "Sen", 
      "withdrawn_at": null
    }
  ], 
  "enacted_as": null, 
  "history": {
    "active": false, 
    "awaiting_signature": false, 
    "enacted": false, 
    "vetoed": false
  }, 
  "introduced_at": "2014-09-15", 
  "number": "2804", 
  "official_title": "A bill to amend the Public Health Service Act with regard to research on asthma, and for other purposes.", 
  "popular_title": null, 
  "related_bills": [], 
  "short_title": "Family Asthma Act", 
  "sponsor": {
    "district": null, 
    "name": "Gillibrand, Kirsten E.", 
    "state": "NY", 
    "thomas_id": "01866", 
    "title": "Sen", 
    "type": "person"
  }, 
  "status": "REFERRED", 
  "status_at": "2014-09-15", 
  "subjects": [
    "Cardiovascular and respiratory health", 
    "Child health", 
    "Congressional oversight", 
    "Government information and archives", 
    "Health", 
    "Health information and medical records", 
    "Health programs administration and funding", 
    "Health promotion and preventive care", 
    "Intergovernmental relations", 
    "Medical research", 
    "Research administration and funding", 
    "State and local government operations"
  ], 
  "subjects_top_term": "Health", 
  "summary": null, 
  "titles": [
    {
      "as": "introduced", 
      "is_for_portion": false, 
      "title": "Family Asthma Act", 
      "type": "short"
    }, 
    {
      "as": "introduced", 
      "is_for_portion": false, 
      "title": "A bill to amend the Public Health Service Act with regard to research on asthma, and for other purposes.", 
      "type": "official"
    }
  ], 
  "updated_at": "2014-10-25T07:42:00-04:00"
}