{
  "actions": [
    {
      "acted_at": "2014-06-12", 
      "committees": [
        "HSII"
      ], 
      "references": [], 
      "status": "REFERRED", 
      "text": "Referred to the House Committee on Natural Resources.", 
      "type": "referral"
    }, 
    {
      "acted_at": "2014-06-17", 
      "in_committee": null, 
      "references": [], 
      "text": "Referred to the Subcommittee Indian and Alaska Native Affairs.", 
      "type": "referral"
    }, 
    {
      "acted_at": "2014-06-17", 
      "in_committee": null, 
      "references": [], 
      "text": "Referred to the Subcommittee on Public Lands and Environmental Regulation.", 
      "type": "referral"
    }, 
    {
      "acted_at": "2014-07-15", 
      "in_committee": null, 
      "in_subcommittee": null, 
      "references": [], 
      "text": "Subcommittee Hearings Held.", 
      "type": "action"
    }, 
    {
      "acted_at": "2014-07-30", 
      "in_committee": null, 
      "references": [], 
      "text": "Subcommittee on Public Lands and Environmental Regulation Discharged.", 
      "type": "action"
    }, 
    {
      "acted_at": "2014-07-30", 
      "in_committee": null, 
      "references": [], 
      "text": "Subcommittee Indian and Alaska Native Affairs Discharged.", 
      "type": "action"
    }, 
    {
      "acted_at": "2014-07-30", 
      "in_committee": null, 
      "references": [], 
      "text": "Committee Consideration and Mark-up Session Held.", 
      "type": "action"
    }, 
    {
      "acted_at": "2014-07-30", 
      "in_committee": null, 
      "references": [], 
      "status": "REPORTED", 
      "text": "Ordered to be Reported (Amended) by Unanimous Consent.", 
      "type": "calendar"
    }, 
    {
      "acted_at": "2014-09-19T12:31:00-04:00", 
      "committees": [
        "HSII"
      ], 
      "references": [], 
      "text": "Reported (Amended) by the Committee on Natural Resources. H. Rept. 113-606.", 
      "type": "action"
    }, 
    {
      "acted_at": "2014-09-19T12:31:00-04:00", 
      "calendar": "Union", 
      "number": "450", 
      "references": [], 
      "text": "Placed on the Union Calendar, Calendar No. 450.", 
      "type": "calendar", 
      "under": null
    }
  ], 
  "amendments": [], 
  "bill_id": "hr4867-113", 
  "bill_type": "hr", 
  "by_request": false, 
  "committees": [
    {
      "activity": [
        "referral", 
        "markup", 
        "reporting"
      ], 
      "committee": "House Natural Resources", 
      "committee_id": "HSII"
    }, 
    {
      "activity": [
        "referral", 
        "hearings", 
        "discharged"
      ], 
      "committee": "House Natural Resources", 
      "committee_id": "HSII", 
      "subcommittee": "Subcommittee on Indian and Alaska Native Affairs", 
      "subcommittee_id": "24"
    }, 
    {
      "activity": [
        "referral", 
        "discharged"
      ], 
      "committee": "House Natural Resources", 
      "committee_id": "HSII", 
      "subcommittee": "Subcommittee on Public Lands and Environmental Regulation", 
      "subcommittee_id": "10"
    }
  ], 
  "congress": "113", 
  "cosponsors": [
    {
      "district": "29", 
      "name": "Cardenas, Tony", 
      "sponsored_at": "2014-07-11", 
      "state": "CA", 
      "thomas_id": "02107", 
      "title": "Rep", 
      "withdrawn_at": null
    }, 
    {
      "district": "8", 
      "name": "Cook, Paul", 
      "sponsored_at": "2014-06-12", 
      "state": "CA", 
      "thomas_id": "02103", 
      "title": "Rep", 
      "withdrawn_at": null
    }, 
    {
      "district": "1", 
      "name": "LaMalfa, Doug", 
      "sponsored_at": "2014-07-15", 
      "state": "CA", 
      "thomas_id": "02100", 
      "title": "Rep", 
      "withdrawn_at": null
    }
  ], 
  "enacted_as": null, 
  "history": {
    "active": true, 
    "active_at": "2014-07-15", 
    "awaiting_signature": false, 
    "enacted": false, 
    "vetoed": false
  }, 
  "introduced_at": "2014-06-12", 
  "number": "4867", 
  "official_title": "To provide for certain land to be taken into trust for the benefit of Morongo Band of Mission Indians, and for other purposes.", 
  "popular_title": null, 
  "related_bills": [
    {
      "bill_id": "s2847-113", 
      "reason": "related", 
      "type": "bill"
    }
  ], 
  "short_title": "Economic Development Through Tribal Land Exchange Act", 
  "sponsor": {
    "district": "36", 
    "name": "Ruiz, Raul", 
    "state": "CA", 
    "thomas_id": "02109", 
    "title": "Rep", 
    "type": "person"
  }, 
  "status": "REPORTED", 
  "status_at": "2014-07-30", 
  "subjects": [
    "California", 
    "Indian lands and resources rights", 
    "Land transfers", 
    "Native Americans"
  ], 
  "subjects_top_term": "Native Americans", 
  "summary": null, 
  "titles": [
    {
      "as": "introduced", 
      "is_for_portion": false, 
      "title": "Economic Development Through Tribal Land Exchange Act", 
      "type": "short"
    }, 
    {
      "as": "reported to house", 
      "is_for_portion": false, 
      "title": "Economic Development Through Tribal Land Exchange Act", 
      "type": "short"
    }, 
    {
      "as": "introduced", 
      "is_for_portion": false, 
      "title": "To provide for certain land to be taken into trust for the benefit of Morongo Band of Mission Indians, and for other purposes.", 
      "type": "official"
    }
  ], 
  "updated_at": "2014-10-25T07:03:23-04:00"
}